fastapiusers_edgedb/__init__.py
fastapiusers_edgedb/access_token.py
fastapiusers_edgedb/py.typed
fastapiusers_edgedb/user_api.py
fastapiusers_edgedb-0.2.2.dist-info/LICENSE
fastapiusers_edgedb-0.2.2.dist-info/WHEEL
fastapiusers_edgedb-0.2.2.dist-info/METADATA
fastapiusers_edgedb-0.2.2.dist-info/RECORD
