Metadata-Version: 2.1
Name: fastapiusers-edgedb
Version: 0.2.2
Summary: FastAPI Users - Database adapter for EdgeDB
Author-email: 0xsirsaif <sirsaif99@gmail.com>
Requires-Python: >=3.7
Classifier: License :: OSI Approved :: MIT License
Classifier: Development Status :: 4 - Beta
Classifier: Framework :: FastAPI
Classifier: Framework :: AsyncIO
Classifier: Intended Audience :: Developers
Classifier: Programming Language :: Python :: 3.7
Classifier: Programming Language :: Python :: 3.8
Classifier: Programming Language :: Python :: 3.9
Classifier: Programming Language :: Python :: 3.10
Classifier: Programming Language :: Python :: 3 :: Only
Classifier: Topic :: Internet :: WWW/HTTP :: Session
Requires-Dist: fastapi-users >= 10.0.0
Requires-Dist: edgedb >= 1.2.0
Requires-Dist: flake8 ; extra == "dev"
Requires-Dist: pytest ; extra == "dev"
Requires-Dist: requests ; extra == "dev"
Requires-Dist: isort ; extra == "dev"
Requires-Dist: pytest-asyncio ; extra == "dev"
Requires-Dist: flake8-docstrings ; extra == "dev"
Requires-Dist: black ; extra == "dev"
Requires-Dist: mypy ; extra == "dev"
Requires-Dist: codecov ; extra == "dev"
Requires-Dist: pytest-cov ; extra == "dev"
Requires-Dist: pytest-mock ; extra == "dev"
Requires-Dist: asynctest ; extra == "dev"
Requires-Dist: flit ; extra == "dev"
Requires-Dist: bumpversion ; extra == "dev"
Requires-Dist: httpx ; extra == "dev"
Requires-Dist: asgi_lifespan ; extra == "dev"
Project-URL: Documentation, https://fastapi-users.github.io/fastapi-users
Provides-Extra: dev
